xserverpy/__init__.py
xserverpy/xserverpy.py
xserverpy/display/__init__.py
xserverpy/display/bots_printer.py
xserverpy/display/integrations_printer.py
xserverpy/lib/__init__.py
xserverpy/lib/base_service.py
xserverpy/lib/bot.py
xserverpy/lib/bots.py
xserverpy/lib/cli.py
xserverpy/lib/integration.py
xserverpy/lib/integration_watcher.py
xserverpy/lib/integrations.py
xserverpy/lib/user.py
xserverpy/lib/xcode_server.py
xserverpy/utils/__init__.py
xserverpy/utils/config.py
xserverpy/utils/porgress.py
xserverpy/utils/settings.py
xserverpy/utils/version.py
xserverpy-0.2.2.dist-info/DESCRIPTION.rst
xserverpy-0.2.2.dist-info/entry_points.txt
xserverpy-0.2.2.dist-info/METADATA
xserverpy-0.2.2.dist-info/metadata.json
xserverpy-0.2.2.dist-info/pbr.json
xserverpy-0.2.2.dist-info/RECORD
xserverpy-0.2.2.dist-info/top_level.txt
xserverpy-0.2.2.dist-info/WHEEL
