Metadata-Version: 2.0
Name: xserverpy
Version: 0.2.2
Summary: Python Boilerplate contains all the boilerplate you need to create a Python package.
Home-page: https://github.com/oarrabi/xserverpy
Author: Omar Abdelhafith
Author-email: o.arrabi@me.com
License: BSD
Keywords: xserverpy
Platform: UNKNOWN
Classifier: Development Status :: 2 - Pre-Alpha
Classifier: Intended Audience :: Developers
Classifier: License :: OSI Approved :: BSD License
Classifier: Natural Language :: English
Classifier: Programming Language :: Python :: 2
Classifier: Programming Language :: Python :: 2.6
Classifier: Programming Language :: Python :: 2.7
Classifier: Programming Language :: Python :: 3
Classifier: Programming Language :: Python :: 3.3
Classifier: Programming Language :: Python :: 3.4
Requires-Dist: requests
Requires-Dist: python-dateutil
Requires-Dist: termcolor
Requires-Dist: tabulate
Requires-Dist: pytz
Requires-Dist: tzlocal
